djcron_agent-0.0.8.dist-info/metadata.json
djcron_agent-0.0.8.dist-info/METADATA
djcron_agent-0.0.8.dist-info/WHEEL
djcron_agent-0.0.8.dist-info/RECORD
djcron_agent-0.0.8.dist-info/top_level.txt
djcron_agent-0.0.8.dist-info/DESCRIPTION.rst
djcron_agent/agent.py
djcron_agent/tasks.py
djcron_agent/versions.py
djcron_agent/__init__.py
djcron_agent/types.py
djcron_agent/__main__.py
djcron_agent/settings/celery.py
djcron_agent/settings/__init__.py
