Metadata-Version: 2.0
Name: djcron-agent
Version: 0.0.8
Summary: Distributed cron manager agent
Home-page: https://github.com/djcron-project/djcron-agent
Author: Miguel Ángel García
Author-email: miguelangel.garcia@gmail.com
License: Affero
Keywords: distributed cron
Platform: UNKNOWN
Classifier: Development Status :: 4 - Beta
Classifier: Programming Language :: Python :: 2.6
Classifier: Programming Language :: Python :: 2.7
Classifier: Programming Language :: Python :: 3.2
Classifier: Programming Language :: Python :: 3.3
Classifier: Programming Language :: Python :: 3.4
Classifier: Environment :: Console
Classifier: Intended Audience :: Developers
Classifier: License :: OSI Approved :: GNU Affero General Public License v3
Classifier: Operating System :: OS Independent
Requires-Dist: celery (>=3.1.12)
Requires-Dist: psutil (>=2.1.3)
Provides-Extra: redis
Requires-Dist: redis (>=2.10.3); extra == 'redis'
